Metadata-Version: 2.1
Name: Odroid.GPIO
Version: 0.0.3
Summary: A module to control Odroid GPIO channels
Home-page: https://github.com/hhk7734/odroid_gpio
Author: Hyeonki Hong
Author-email: hhk7734@gmail.com
License: MIT
Project-URL: Source, https://github.com/hhk7734/odroid_gpio
Keywords: Odroid,GPIO
Platform: UNKNOWN
Classifier: Programming Language :: Python :: 3
Classifier: License :: OSI Approved :: MIT License
Classifier: Operating System :: POSIX :: Linux
Classifier: Intended Audience :: Developers
Classifier: Topic :: Software Development
Classifier: Topic :: System :: Hardware
